LICENSE
binfootprint/__init__.py
binfootprint/binfootprint.py
binfootprint/util.py
binfootprint-1.2.2.dist-info/LICENSE
binfootprint-1.2.2.dist-info/METADATA
binfootprint-1.2.2.dist-info/WHEEL
binfootprint-1.2.2.dist-info/RECORD
