Metadata-Version: 2.1
Name: binfootprint
Version: 1.2.2
Summary: unique serialization of python objetcs
Home-page: https://github.com/richard-hartmann/binfootprint
License: MIT
Keywords: serialization,binary key,cache,function cache,scientific computing
Author: Richard Hartmann
Requires-Python: >=3.8,<4.0
Classifier: Environment :: Console
Classifier: License :: OSI Approved :: MIT License
Classifier: Operating System :: OS Independent
Classifier: Programming Language :: Python :: 3
Classifier: Programming Language :: Python :: 3.8
Classifier: Programming Language :: Python :: 3.9
Classifier: Programming Language :: Python :: 3.10
Classifier: Programming Language :: Python :: 3.11
Classifier: Topic :: Database
Classifier: Topic :: Software Development :: Libraries
Requires-Dist: black (>=22.0.0)
Requires-Dist: numpy (>=1.24.1,<2.0.0)
Requires-Dist: pytest (>=7.0.0)
Project-URL: Repository, https://github.com/richard-hartmann/binfootprint
